matrix_legend.py
matplotlib_matrix_legend-0.0.3.dist-info/METADATA
matplotlib_matrix_legend-0.0.3.dist-info/WHEEL
matplotlib_matrix_legend-0.0.3.dist-info/licenses/LICENSE
matplotlib_matrix_legend-0.0.3.dist-info/RECORD
