Metadata-Version: 2.4
Name: matplotlib-matrix-legend
Version: 0.0.3
Summary: Matrix legend layout for matplotlib
Project-URL: Homepage, https://github.com/nj-vs-vh/matplotlib-matrix-legend
Project-URL: Issues, https://github.com/nj-vs-vh/matplotlib-matrix-legend/issues
Author-email: Igor Vaiman <gosha.vaiman@gmail.com>
License-Expression: MIT
License-File: LICENSE
Classifier: Operating System :: OS Independent
Classifier: Programming Language :: Python :: 3
Requires-Python: >=3.9
